robogram/__init__.py
robogram/__version__.py
robogram/api_telegram_bot.py
robogram/errors.py
robogram-0.1.0.dist-info/LICENSE
robogram-0.1.0.dist-info/METADATA
robogram-0.1.0.dist-info/WHEEL
robogram-0.1.0.dist-info/top_level.txt
robogram-0.1.0.dist-info/RECORD
