Metadata-Version: 2.1
Name: robogram
Version: 0.1.0
Summary: Minimal Telegram Bot API wrapper to send messages - to user, channel, or group.
Home-page: https://github.com/rnag/robogram
Author: Ritvik Nag
Author-email: me@ritviknag.com
License: MIT
Project-URL: Documentation, https://robogram.readthedocs.io
Project-URL: Source, https://github.com/rnag/robogram
Keywords: telegram,bot,api,robogram,robot
Platform: UNKNOWN
Classifier: Development Status :: 5 - Production/Stable
Classifier: Intended Audience :: Developers
Classifier: License :: OSI Approved :: MIT License
Classifier: Natural Language :: English
Classifier: Programming Language :: Python :: 3 :: Only
Classifier: Programming Language :: Python :: 3
Classifier: Programming Language :: Python :: 3.8
Classifier: Programming Language :: Python :: 3.9
Classifier: Programming Language :: Python :: 3.10
Classifier: Programming Language :: Python :: 3.11
Classifier: Programming Language :: Python :: 3.12
Classifier: Programming Language :: Python
Requires-Dist: requests
